{"name": "warbrig", "orientations": {"11": {"x": 162, "offsetx": 0, "height": 59, "width": 54, "y": 0, "offsety": 15}, "7": {"x": 810, "offsetx": 0, "height": 59, "width": 54, "y": 0, "offsety": 15}, "15": {"x": 378, "offsetx": 0, "height": 59, "width": 54, "y": 0, "offsety": 15}, "8": {"x": 0, "offsetx": 0, "height": 59, "width": 54, "y": 0, "offsety": 15}, "9": {"x": 54, "offsetx": 0, "height": 59, "width": 54, "y": 0, "offsety": 15}, "1": {"x": 486, "offsetx": 0, "height": 59, "width": 54, "y": 0, "offsety": 15}, "2": {"x": 540, "offsetx": 0, "height": 59, "width": 54, "y": 0, "offsety": 15}, "6": {"x": 756, "offsetx": 0, "height": 59, "width": 54, "y": 0, "offsety": 15}, "10": {"x": 108, "offsetx": 0, "height": 59, "width": 54, "y": 0, "offsety": 15}, "4": {"x": 648, "offsetx": 0, "height": 59, "width": 54, "y": 0, "offsety": 15}, "5": {"x": 702, "offsetx": 0, "height": 59, "width": 54, "y": 0, "offsety": 15}, "0": {"x": 432, "offsetx": 0, "height": 59, "width": 54, "y": 0, "offsety": 15}, "14": {"x": 324, "offsetx": 0, "height": 59, "width": 54, "y": 0, "offsety": 15}, "3": {"x": 594, "offsetx": 0, "height": 59, "width": 54, "y": 0, "offsety": 15}, "13": {"x": 270, "offsetx": 0, "height": 59, "width": 54, "y": 0, "offsety": 15}, "12": {"x": 216, "offsetx": 0, "height": 59, "width": 54, "y": 0, "offsety": 15}}}